PyLiteDB/__init__.py
PyLiteDB/__main__.py
PyLiteDB/btree.py
PyLiteDB/cli.py
PyLiteDB/crypto.py
PyLiteDB/engine.py
PyLiteDB/pager.py
PyLiteDB/parser.py
PyLiteDB/storage.py
PyLiteDB/wal.py
pylitedb_engine-1.0.0.dist-info/licenses/LICENSE.md
pylitedb_engine-1.0.0.dist-info/METADATA
pylitedb_engine-1.0.0.dist-info/WHEEL
pylitedb_engine-1.0.0.dist-info/entry_points.txt
pylitedb_engine-1.0.0.dist-info/top_level.txt
pylitedb_engine-1.0.0.dist-info/RECORD
