Metadata-Version: 2.4
Name: pylitedb-engine
Version: 1.0.0
Summary: A lightweight Python database engine that stores JSON-like records with optional encryption support.
Author: Sreeraj S Kurup
License: MIT License
Keywords: database,database-engine,json,json-database,lightweight-database,python-database,encryption,encrypted-database,cli,storage
Classifier: Programming Language :: Python :: 3
Classifier: Operating System :: OS Independent
Classifier: License :: OSI Approved :: MIT License
Requires-Python: >=3.10
License-File: LICENSE.md
Requires-Dist: cryptography>=41.0.0
Dynamic: license-file
